odoo10_addon_l10n_es_partner_mercantil-10.0.1.0.0-py2.7-nspkg.pth
odoo10_addon_l10n_es_partner_mercantil-10.0.1.0.0.dist-info/top_level.txt
odoo10_addon_l10n_es_partner_mercantil-10.0.1.0.0.dist-info/WHEEL
odoo10_addon_l10n_es_partner_mercantil-10.0.1.0.0.dist-info/RECORD
odoo10_addon_l10n_es_partner_mercantil-10.0.1.0.0.dist-info/metadata.json
odoo10_addon_l10n_es_partner_mercantil-10.0.1.0.0.dist-info/DESCRIPTION.rst
odoo10_addon_l10n_es_partner_mercantil-10.0.1.0.0.dist-info/METADATA
odoo10_addon_l10n_es_partner_mercantil-10.0.1.0.0.dist-info/namespace_packages.txt
odoo/addons/l10n_es_partner_mercantil/__manifest__.py
odoo/addons/l10n_es_partner_mercantil/__init__.py
odoo/addons/l10n_es_partner_mercantil/README.rst
odoo/addons/l10n_es_partner_mercantil/models/__init__.py
odoo/addons/l10n_es_partner_mercantil/models/partner_es.py
odoo/addons/l10n_es_partner_mercantil/i18n/pt.po
odoo/addons/l10n_es_partner_mercantil/i18n/es.po
odoo/addons/l10n_es_partner_mercantil/i18n/hr.po
odoo/addons/l10n_es_partner_mercantil/i18n/bg.po
odoo/addons/l10n_es_partner_mercantil/i18n/gl.po
odoo/addons/l10n_es_partner_mercantil/i18n/ca.po
odoo/addons/l10n_es_partner_mercantil/i18n/sl.po
odoo/addons/l10n_es_partner_mercantil/i18n/nl.po
odoo/addons/l10n_es_partner_mercantil/i18n/fr.po
odoo/addons/l10n_es_partner_mercantil/i18n/pt_BR.po
odoo/addons/l10n_es_partner_mercantil/views/res_partner_view.xml
odoo/addons/l10n_es_partner_mercantil/static/description/icon.svg
odoo/addons/l10n_es_partner_mercantil/static/description/icon.png
